mesh_illustris/__init__.py
mesh_illustris/core.py
mesh_illustris/il_util.py
mesh_illustris/loader.py
mesh_illustris/mesh.py
mesh_illustris/tests/__init__.py
mesh_illustris/tests/run.py
mesh_illustris/tests/test_core.py
mesh_illustris/tests/test_il_util.py
mesh_illustris/tests/test_import.py
mesh_illustris/tests/test_loader.py
mesh_illustris/tests/test_mesh.py
mesh_illustris-0.2.dist-info/LICENSE
mesh_illustris-0.2.dist-info/METADATA
mesh_illustris-0.2.dist-info/WHEEL
mesh_illustris-0.2.dist-info/top_level.txt
mesh_illustris-0.2.dist-info/RECORD
