Metadata-Version: 2.1
Name: mesh-illustris
Version: 0.2
Summary: Load Illustris with mesh.
Home-page: https://github.com/EnthalpyBill/mesh_illustris
Author: Bill Chen <ybchen@umich.edu>
Maintainer: Bill Chen <ybchen@umich.edu>
License: MIT
Platform: UNKNOWN
Classifier: Programming Language :: Python :: 3
Classifier: License :: OSI Approved :: MIT License
Classifier: Operating System :: OS Independent
Requires-Python: >=3.8
License-File: LICENSE
Requires-Dist: numpy (>=1.18)
Requires-Dist: h5py (>=2.10)
Requires-Dist: numba (>=0.50)
